data_go_mcp/__init__.py
data_go_mcp/fsc_financial_info/__init__.py
data_go_mcp/fsc_financial_info/api_client.py
data_go_mcp/fsc_financial_info/models.py
data_go_mcp/fsc_financial_info/server.py
data_go_mcp_fsc_financial_info-0.2.0.dist-info/METADATA
data_go_mcp_fsc_financial_info-0.2.0.dist-info/WHEEL
data_go_mcp_fsc_financial_info-0.2.0.dist-info/entry_points.txt
data_go_mcp_fsc_financial_info-0.2.0.dist-info/RECORD
