Metadata-Version: 2.4
Name: data-go-mcp.fsc-financial-info
Version: 0.2.0
Summary: MCP server for Korea FSC Corporate Financial Information API (금융위원회 기업 재무정보)
Project-URL: Homepage, https://github.com/Koomook/data-go-mcp-servers
Project-URL: Repository, https://github.com/Koomook/data-go-mcp-servers
Project-URL: Documentation, https://github.com/Koomook/data-go-mcp-servers#fsc-financial-info
Project-URL: Issues, https://github.com/Koomook/data-go-mcp-servers/issues
Author-email: Your Name <your.email@example.com>
License: Apache-2.0
Keywords: corporate,data.go.kr,financial,fsc,korea,llm,mcp,openapi
Requires-Python: >=3.10
Requires-Dist: httpx>=0.24.0
Requires-Dist: mcp>=1.0.0
Requires-Dist: pydantic>=2.0.0
Requires-Dist: python-dotenv>=1.0.0
Requires-Dist: xmltodict>=0.13.0
